{
  "data": [
    [
      [
        1,
        null,
        0
      ],
      [
        0.4183768656716418,
        0.13225293159484863,
        {
          "__enum__": "StatusType.SUCCESS"
        },
        {}
      ]
    ],
    [
      [
        2,
        null,
        0
      ],
      [
        2147483647.0,
        0.021672964096069336,
        {
          "__enum__": "StatusType.CRASHED"
        },
        {}
      ]
    ],
    [
      [
        3,
        null,
        0
      ],
      [
        2147483647.0,
        0.028046131134033203,
        {
          "__enum__": "StatusType.CRASHED"
        },
        {}
      ]
    ]
  ],
  "config_origins": {
    "1": "Default",
    "2": "Random Search",
    "3": "Random Search (sorted)"
  },
  "configs": {
    "1": {
      "KNNEstimator__leaf_size": 30,
      "KNNEstimator__metric": "minkowski",
      "KNNEstimator__n_neighbors": 5,
      "ReliefFSelection__num_features": 20,
      "ReliefFSelection__num_neighbors": 20,
      "KNNEstimator__p": 2
    },
    "2": {
      "KNNEstimator__leaf_size": 10,
      "KNNEstimator__metric": "manhattan",
      "KNNEstimator__n_neighbors": 62,
      "ReliefFSelection__num_features": 40,
      "ReliefFSelection__num_neighbors": 60
    },
    "3": {
      "KNNEstimator__leaf_size": 55,
      "KNNEstimator__metric": "manhattan",
      "KNNEstimator__n_neighbors": 44,
      "ReliefFSelection__num_features": 30,
      "ReliefFSelection__num_neighbors": 46
    }
  }
}