{
  "data": [
    [
      [
        1,
        null,
        0
      ],
      [
        0.4416977611940298,
        0.17284703254699707,
        {
          "__enum__": "StatusType.SUCCESS"
        },
        {}
      ]
    ],
    [
      [
        2,
        null,
        0
      ],
      [
        2147483647.0,
        0.031166791915893555,
        {
          "__enum__": "StatusType.CRASHED"
        },
        {}
      ]
    ],
    [
      [
        3,
        null,
        0
      ],
      [
        2147483647.0,
        0.021547794342041016,
        {
          "__enum__": "StatusType.CRASHED"
        },
        {}
      ]
    ]
  ],
  "config_origins": {
    "1": "Default",
    "2": "Random Search",
    "3": "Random Search (sorted)"
  },
  "configs": {
    "1": {
      "LogRegEstimator__C": 1.0,
      "LogRegEstimator__penalty": "l2",
      "LogRegEstimator__random_state": 500,
      "ReliefFSelection__num_features": 20,
      "ReliefFSelection__num_neighbors": 20
    },
    "2": {
      "LogRegEstimator__C": 418.84202735210323,
      "LogRegEstimator__penalty": "l2",
      "LogRegEstimator__random_state": 720,
      "ReliefFSelection__num_features": 27,
      "ReliefFSelection__num_neighbors": 63
    },
    "3": {
      "LogRegEstimator__C": 503.7102654625573,
      "LogRegEstimator__penalty": "l2",
      "LogRegEstimator__random_state": 427,
      "ReliefFSelection__num_features": 30,
      "ReliefFSelection__num_neighbors": 46
    }
  }
}